ipython_sparql/__init__.py
ipython_sparql/sparql.py
ipython_sparql-0.1.dist-info/DESCRIPTION.rst
ipython_sparql-0.1.dist-info/METADATA
ipython_sparql-0.1.dist-info/RECORD
ipython_sparql-0.1.dist-info/WHEEL
ipython_sparql-0.1.dist-info/metadata.json
ipython_sparql-0.1.dist-info/top_level.txt
