Metadata-Version: 2.0
Name: ipython-sparql
Version: 0.1
Summary: Jupyter/IPython Extension for Sparql queries
Home-page: https://github.com/baito/ipython_sparql
Author: Bruno de Oliveira
Author-email: ddd@dd.com.br
License: MIT
Keywords: sparql jupyter extension magic ipython
Platform: UNKNOWN
Requires-Dist: SPARQLWrapper
Requires-Dist: ipython
Requires-Dist: tabulate
